ncvxsp/__init__.py
ncvxsp/_version.py
ncvxsp/linear_model/__init__.py
ncvxsp/linear_model/scad_cd_fast.cp39-win_amd64.pyd
ncvxsp/linear_model/scad_coordinate_descent.py
ncvxsp/tests/__init__.py
ncvxsp/tests/test_scad.py
ncvx_sparse-0.0.1.dev3.dist-info/LICENSE
ncvx_sparse-0.0.1.dev3.dist-info/METADATA
ncvx_sparse-0.0.1.dev3.dist-info/WHEEL
ncvx_sparse-0.0.1.dev3.dist-info/top_level.txt
ncvx_sparse-0.0.1.dev3.dist-info/RECORD
