Metadata-Version: 2.1
Name: ncvx-sparse
Version: 0.0.1.dev3
Summary: Scikit-learn compatible implementation of nonconvex sparse estimators for single- and multi-task linear regressions (e.g. SCAD, MCP, l1-group-SCAD, etc).
Home-page: https://github.com/scikit-learn-contrib/Clej/ncvx_estimators
Download-URL: https://github.com/scikit-learn-contrib/Clej/ncvx_estimators
Maintainer: Clement Lejeune
Maintainer-email: clement.lejeune@irit.fr
License: BSD (3-clause)
Platform: UNKNOWN
Classifier: Intended Audience :: Science/Research
Classifier: Intended Audience :: Developers
Classifier: License :: OSI Approved
Classifier: Programming Language :: Python
Classifier: Topic :: Software Development
Classifier: Topic :: Scientific/Engineering
Classifier: Operating System :: Microsoft :: Windows
Classifier: Operating System :: POSIX
Classifier: Operating System :: Unix
Classifier: Operating System :: MacOS
Classifier: Programming Language :: Python :: 3.6
Classifier: Programming Language :: Python :: 3.7
Requires-Python: >=3.6
License-File: LICENSE
Requires-Dist: numpy
Requires-Dist: scipy
Requires-Dist: scikit-learn (>=0.23)
Requires-Dist: cython (>=0.26)
Requires-Dist: pandas (==0.25)
Provides-Extra: docs
Requires-Dist: sphinx ; extra == 'docs'
Requires-Dist: sphinx-gallery ; extra == 'docs'
Requires-Dist: sphinx-rtd-theme ; extra == 'docs'
Requires-Dist: numpydoc ; extra == 'docs'
Requires-Dist: matplotlib ; extra == 'docs'
Provides-Extra: tests
Requires-Dist: pytest ; extra == 'tests'
Requires-Dist: pytest-cov ; extra == 'tests'
